claude_parser/__init__.py
claude_parser/analytics/__init__.py
claude_parser/analytics/billing.py
claude_parser/analytics/core.py
claude_parser/analytics/litellm_adapter.py
claude_parser/analytics/projects.py
claude_parser/analytics/tools.py
claude_parser/cli/__init__.py
claude_parser/cli/cg.py
claude_parser/cli/cg_advanced.py
claude_parser/cli/cg_basic.py
claude_parser/cli/cg_reflog.py
claude_parser/cli/cg_reset.py
claude_parser/cli/cg_restore.py
claude_parser/cli/ch.py
claude_parser/discovery/__init__.py
claude_parser/discovery/core.py
claude_parser/filtering/__init__.py
claude_parser/filtering/filters.py
claude_parser/hooks/CONTRACT.md
claude_parser/hooks/README.md
claude_parser/hooks/__init__.py
claude_parser/hooks/aggregator.py
claude_parser/hooks/api.py
claude_parser/hooks/app.py
claude_parser/hooks/executor.py
claude_parser/hooks/extraction.py
claude_parser/hooks/handlers.py
claude_parser/hooks/models.py
claude_parser/hooks/request.py
claude_parser/hooks/utils.py
claude_parser/loaders/discovery.py
claude_parser/loaders/session.py
claude_parser/main.py
claude_parser/messages/utils.py
claude_parser/models/__init__.py
claude_parser/navigation/__init__.py
claude_parser/navigation/checkpoint.py
claude_parser/navigation/core.py
claude_parser/navigation/session_boundaries.py
claude_parser/navigation/timeline.py
claude_parser/operations/__init__.py
claude_parser/operations/core.py
claude_parser/operations/diff_ops.py
claude_parser/operations/file_ops.py
claude_parser/operations/restore_ops.py
claude_parser/queries/__init__.py
claude_parser/queries/blame_queries.py
claude_parser/queries/find_queries.py
claude_parser/queries/query_utils.py
claude_parser/queries/reflog_queries.py
claude_parser/queries/schema_models.py
claude_parser/queries/session_queries.py
claude_parser/queries/token_queries.py
claude_parser/session/__init__.py
claude_parser/session/core.py
claude_parser/settings.py
claude_parser/storage/engine.py
claude_parser/storage/jsonl_engine.py
claude_parser-2.0.0.dist-info/METADATA
claude_parser-2.0.0.dist-info/WHEEL
claude_parser-2.0.0.dist-info/entry_points.txt
claude_parser-2.0.0.dist-info/RECORD
