Metadata-Version: 2.4
Name: claude-parser
Version: 2.0.0
Summary: Parse and analyze Claude Code JSONL exports
Author: Your Name
Author-email: you@example.com
Requires-Python: >=3.10,<4.0
Classifier: Programming Language :: Python :: 3
Classifier: Programming Language :: Python :: 3.10
Classifier: Programming Language :: Python :: 3.11
Classifier: Programming Language :: Python :: 3.12
Classifier: Programming Language :: Python :: 3.13
Classifier: Programming Language :: Python :: 3.14
Requires-Dist: aiofiles (>=23.0.0,<24.0.0)
Requires-Dist: click (>=8.1.0,<9.0.0)
Requires-Dist: deepdiff (>=8.6.0,<9.0.0)
Requires-Dist: diskcache (>=5.6.3,<6.0.0)
Requires-Dist: duckdb (>=1.3.2,<2.0.0)
Requires-Dist: funcy (>=2.0,<3.0)
Requires-Dist: gitpython (>=3.1.45,<4.0.0)
Requires-Dist: glom (>=22.1.0,<23.0.0)
Requires-Dist: httpx (>=0.27.0,<0.28.0)
Requires-Dist: jmespath (>=1.0.1,<2.0.0)
Requires-Dist: lazy-object-proxy (>=1.10.0,<2.0.0)
Requires-Dist: loguru (>=0.7.0,<0.8.0)
Requires-Dist: more-itertools (>=10.7.0,<11.0.0)
Requires-Dist: pendulum (>=3.0.0,<4.0.0)
Requires-Dist: polars (>=1.0.0,<2.0.0)
Requires-Dist: project-root-finder (>=1.9,<2.0)
Requires-Dist: pydantic (>=2.11.9,<3.0.0)
Requires-Dist: pydantic-settings (>=2.10.1,<3.0.0)
Requires-Dist: pygit2 (>=1.15.0,<2.0.0)
Requires-Dist: python-dotenv (>=1.0.0,<2.0.0)
Requires-Dist: rich (>=13.0.0,<14.0.0)
Requires-Dist: tenacity (>=9.0.0,<10.0.0)
Requires-Dist: tiktoken (>=0.8.0,<0.9.0)
Requires-Dist: toolz (>=1.0.0,<2.0.0)
Requires-Dist: typer (>=0.15.0,<0.16.0)
Requires-Dist: watchfiles (>=0.21.0,<0.22.0)
